COPYING
MANIFEST.in
README.rst
requirements.txt
setup.cfg
setup.py
docs/Makefile
docs/conf.py
docs/index.rst
docs/make.bat
docs/_build/doctrees/environment.pickle
docs/_build/doctrees/index.doctree
docs/_build/doctrees/rst/install.doctree
docs/_build/doctrees/rst/license.doctree
docs/_build/doctrees/rst/loading.doctree
docs/_build/doctrees/rst/mapping.doctree
docs/_build/doctrees/rst/samples.doctree
docs/_build/html/.buildinfo
docs/_build/html/genindex.html
docs/_build/html/index.html
docs/_build/html/objects.inv
docs/_build/html/search.html
docs/_build/html/searchindex.js
docs/_build/html/_sources/index.rst.txt
docs/_build/html/_sources/rst/install.rst.txt
docs/_build/html/_sources/rst/license.rst.txt
docs/_build/html/_sources/rst/loading.rst.txt
docs/_build/html/_sources/rst/mapping.rst.txt
docs/_build/html/_sources/rst/samples.rst.txt
docs/_build/html/_static/ajax-loader.gif
docs/_build/html/_static/basic.css
docs/_build/html/_static/comment-bright.png
docs/_build/html/_static/comment-close.png
docs/_build/html/_static/comment.png
docs/_build/html/_static/doctools.js
docs/_build/html/_static/documentation_options.js
docs/_build/html/_static/down-pressed.png
docs/_build/html/_static/down.png
docs/_build/html/_static/file.png
docs/_build/html/_static/jquery-3.2.1.js
docs/_build/html/_static/jquery.js
docs/_build/html/_static/language_data.js
docs/_build/html/_static/minus.png
docs/_build/html/_static/plus.png
docs/_build/html/_static/pygments.css
docs/_build/html/_static/searchtools.js
docs/_build/html/_static/underscore-1.3.1.js
docs/_build/html/_static/underscore.js
docs/_build/html/_static/up-pressed.png
docs/_build/html/_static/up.png
docs/_build/html/_static/websupport.js
docs/_build/html/_static/css/badge_only.css
docs/_build/html/_static/css/theme.css
docs/_build/html/_static/fonts/FontAwesome.otf
docs/_build/html/_static/fonts/fontawesome-webfont.eot
docs/_build/html/_static/fonts/fontawesome-webfont.svg
lib/popEtl.egg-info/PKG-INFO
lib/popEtl.egg-info/SOURCES.txt
lib/popEtl.egg-info/dependency_links.txt
lib/popEtl.egg-info/not-zip-safe
lib/popEtl.egg-info/requires.txt
lib/popEtl.egg-info/top_level.txt
